dash_ai_chat/__init__.py
dash_ai_chat/dash_ai_chat.py
dash_ai_chat/providers.py
dash_ai_chat/py.typed
dash_ai_chat/assets/style.css
dash_ai_chat-0.0.4.dist-info/METADATA
dash_ai_chat-0.0.4.dist-info/WHEEL
dash_ai_chat-0.0.4.dist-info/licenses/LICENSE
dash_ai_chat-0.0.4.dist-info/RECORD
