Metadata-Version: 2.4
Name: dash-ai-chat
Version: 0.0.4
Summary: A customizable LLM chat UI framework built on Plotly Dash
Project-URL: Homepage, https://github.com/eliasdabbas/dash-ai-chat
Project-URL: Documentation, https://github.com/eliasdabbas/dash-ai-chat#readme
Project-URL: Repository, https://github.com/eliasdabbas/dash-ai-chat.git
Project-URL: Bug Tracker, https://github.com/eliasdabbas/dash-ai-chat/issues
Project-URL: Source Code, https://github.com/eliasdabbas/dash-ai-chat
Project-URL: Changelog, https://github.com/eliasdabbas/dash-ai-chat/releases
Author-email: Elias Dabbas <eliasdabbas@gmail.com>
Maintainer-email: Elias Dabbas <eliasdabbas@gmail.com>
License: MIT
License-File: LICENSE
Keywords: ai,anthropic,chat,chatbot,dash,framework,gemini,llm,openai,plotly,ui
Classifier: Development Status :: 3 - Alpha
Classifier: Environment :: Web Environment
Classifier: Framework :: Dash
Classifier: Intended Audience :: Developers
Classifier: License :: OSI Approved :: MIT License
Classifier: Operating System :: OS Independent
Classifier: Programming Language :: Python :: 3
Classifier: Programming Language :: Python :: 3.9
Classifier: Programming Language :: Python :: 3.10
Classifier: Programming Language :: Python :: 3.11
Classifier: Programming Language :: Python :: 3.12
Classifier: Programming Language :: Python :: 3.13
Classifier: Topic :: Internet :: WWW/HTTP :: Dynamic Content
Classifier: Topic :: Scientific/Engineering :: Artificial Intelligence
Classifier: Topic :: Software Development :: Libraries :: Python Modules
Classifier: Topic :: Software Development :: User Interfaces
Requires-Python: >=3.9
Requires-Dist: dash-bootstrap-components>=2.0.3
Requires-Dist: dash>=3.2.0
Provides-Extra: anthropic
Requires-Dist: anthropic>=0.40.0; extra == 'anthropic'
Provides-Extra: gemini
Requires-Dist: google-genai>=1.29.0; extra == 'gemini'
Requires-Dist: google-generativeai>=0.8.0; extra == 'gemini'
Provides-Extra: openai
Requires-Dist: openai>=1.97.1; extra == 'openai'
